COPYRIGHT
MANIFEST.in
Makefile
README
setup.py
test/__init__.py
test/__init__.pyc
test/test_compile.py
test/test_compile.pyc
tiddlywebplugins/__init__.py
tiddlywebplugins/logout.py
tiddlywebplugins.logout.egg-info/PKG-INFO
tiddlywebplugins.logout.egg-info/SOURCES.txt
tiddlywebplugins.logout.egg-info/dependency_links.txt
tiddlywebplugins.logout.egg-info/namespace_packages.txt
tiddlywebplugins.logout.egg-info/not-zip-safe
tiddlywebplugins.logout.egg-info/requires.txt
tiddlywebplugins.logout.egg-info/top_level.txt