Metadata-Version: 1.0
Name: tiddlywebplugins.logout
Version: 1.0
Summary: /logout for TiddlyWeb
Home-page: http://pypi.python.org/pypi/tiddlywebplugins.logout
Author: Chris Dent
Author-email: cdent@peermore.com
License: UNKNOWN
Platform: Posix; MacOS X; Windows
